copypl/_version.py
copypl/copypl.py
copypl-1.0.1.dist-info/LICENSE.txt
copypl-1.0.1.dist-info/METADATA
copypl-1.0.1.dist-info/WHEEL
copypl-1.0.1.dist-info/entry_points.txt
copypl-1.0.1.dist-info/top_level.txt
copypl-1.0.1.dist-info/RECORD
