Metadata-Version: 2.1
Name: copypl
Version: 1.0.1
Summary: A Python script for copying files referenced by m3u/m3u8/pls playlists
Home-page: https://github.com/dgasaway/copypl
Author: David Gasaway
Author-email: dave@gasaway.org
License: GNU GPL v2
Download-URL: https://github.com/dgasaway/copypl/releases
Keywords: audio music playlist
Platform: UNKNOWN
Classifier: Operating System :: OS Independent
Classifier: Programming Language :: Python :: 3
Classifier: Programming Language :: Python :: 3.2
Classifier: Programming Language :: Python :: 3 :: Only
Classifier: License :: OSI Approved :: GNU General Public License v2 or later (GPLv2+)
Classifier: Topic :: Multimedia :: Sound/Audio
Classifier: Development Status :: 5 - Production/Stable
Classifier: Environment :: Console
Classifier: Intended Audience :: End Users/Desktop
Requires-Python: >=3.2
